{
  "type": "FeatureCollection",
  "features": [
    {
      "type": "Feature",
      "geometry": {
        "type": "Point",
        "coordinates": [
          -115.1398,
          36.1699
        ]
      },
      "properties": {
        "name": "The Strip",
        "type": "landmark"
      }
    },
    {
      "type": "Feature",
      "geometry": {
        "type": "Point",
        "coordinates": [
          -115.1398,
          36.1699
        ]
      },
      "properties": {
        "name": "Downtown",
        "type": "landmark"
      }
    },
    {
      "type": "Feature",
      "geometry": {
        "type": "Point",
        "coordinates": [
          -115.14,
          36.17
        ]
      },
      "properties": {
        "name": "Fremont East",
        "type": "landmark"
      }
    },
    {
      "type": "Feature",
      "geometry": {
        "type": "Point",
        "coordinates": [
          -115.33,
          36.15
        ]
      },
      "properties": {
        "name": "Summerlin",
        "type": "landmark"
      }
    },
    {
      "type": "Feature",
      "geometry": {
        "type": "Point",
        "coordinates": [
          -115.1728,
          36.1147
        ]
      },
      "properties": {
        "name": "Welcome to Las Vegas sign",
        "type": "landmark"
      }
    },
    {
      "type": "Feature",
      "geometry": {
        "type": "Point",
        "coordinates": [
          -115.1398,
          36.1699
        ]
      },
      "properties": {
        "name": "The Strip casinos",
        "type": "landmark"
      }
    },
    {
      "type": "Feature",
      "geometry": {
        "type": "Point",
        "coordinates": [
          -115.14,
          36.17
        ]
      },
      "properties": {
        "name": "Fremont Street Experience",
        "type": "landmark"
      }
    }
  ]
}